gdbdbg/__init__.py
gdbdbg/build.py
gdbdbg/dbg.py
gdbdbg/gdbinit.py
gdbdbg/inject.py
gdbdbg/libpython.py
gdbdbg/util.py
gdbdbg/gdb/bin/gcore
gdbdbg/gdb/bin/gdb
gdbdbg/gdb/bin/gdb-add-index
gdbdbg/gdb/bin/gdbserver
gdbdbg/gdb/include/ansidecl.h
gdbdbg/gdb/include/bfd.h
gdbdbg/gdb/include/bfdlink.h
gdbdbg/gdb/include/ctf-api.h
gdbdbg/gdb/include/ctf.h
gdbdbg/gdb/include/diagnostics.h
gdbdbg/gdb/include/dis-asm.h
gdbdbg/gdb/include/gmp.h
gdbdbg/gdb/include/mpf2mpfr.h
gdbdbg/gdb/include/mpfr.h
gdbdbg/gdb/include/plugin-api.h
gdbdbg/gdb/include/sframe-api.h
gdbdbg/gdb/include/sframe.h
gdbdbg/gdb/include/symcat.h
gdbdbg/gdb/include/gdb/jit-reader.h
gdbdbg/gdb/lib/libbfd.a
gdbdbg/gdb/lib/libbfd.la
gdbdbg/gdb/lib/libcrypt.so.1
gdbdbg/gdb/lib/libctf-nobfd.a
gdbdbg/gdb/lib/libctf-nobfd.la
gdbdbg/gdb/lib/libctf.a
gdbdbg/gdb/lib/libctf.la
gdbdbg/gdb/lib/libgmp.a
gdbdbg/gdb/lib/libgmp.la
gdbdbg/gdb/lib/libgmp.so
gdbdbg/gdb/lib/libgmp.so.10
gdbdbg/gdb/lib/libgmp.so.10.5.0
gdbdbg/gdb/lib/libinproctrace.so
gdbdbg/gdb/lib/liblzma.so.5
gdbdbg/gdb/lib/libmpfr.a
gdbdbg/gdb/lib/libmpfr.la
gdbdbg/gdb/lib/libmpfr.so
gdbdbg/gdb/lib/libmpfr.so.6
gdbdbg/gdb/lib/libmpfr.so.6.2.1
gdbdbg/gdb/lib/libncursesw.so.6
gdbdbg/gdb/lib/libopcodes.a
gdbdbg/gdb/lib/libopcodes.la
gdbdbg/gdb/lib/libreadline.so.8
gdbdbg/gdb/lib/libsframe.a
gdbdbg/gdb/lib/libsframe.la
gdbdbg/gdb/lib/libstdc++.so.6
gdbdbg/gdb/lib/libtinfow.so.6
gdbdbg/gdb/lib/libz.so.1
gdbdbg/gdb/lib/pkgconfig/gmp.pc
gdbdbg/gdb/lib/pkgconfig/mpfr.pc
gdbdbg/gdb/share/doc/mpfr/AUTHORS
gdbdbg/gdb/share/doc/mpfr/BUGS
gdbdbg/gdb/share/doc/mpfr/COPYING
gdbdbg/gdb/share/doc/mpfr/COPYING.LESSER
gdbdbg/gdb/share/doc/mpfr/FAQ.html
gdbdbg/gdb/share/doc/mpfr/NEWS
gdbdbg/gdb/share/doc/mpfr/TODO
gdbdbg/gdb/share/doc/mpfr/examples/ReadMe
gdbdbg/gdb/share/doc/mpfr/examples/can_round.c
gdbdbg/gdb/share/doc/mpfr/examples/divworst.c
gdbdbg/gdb/share/doc/mpfr/examples/rndo-add.c
gdbdbg/gdb/share/doc/mpfr/examples/sample.c
gdbdbg-0.2.5.dist-info/LICENSE.md
gdbdbg-0.2.5.dist-info/METADATA
gdbdbg-0.2.5.dist-info/WHEEL
gdbdbg-0.2.5.dist-info/entry_points.txt
gdbdbg-0.2.5.dist-info/top_level.txt
gdbdbg-0.2.5.dist-info/RECORD
