Metadata-Version: 2.1
Name: gdbdbg
Version: 0.2.5
Summary: gdb debugger
Home-page: https://github.com/saltstack/gdbdbg
Author: Daniel A. Wozniak
Author-email: <dwozniak@broadcom.com>
Classifier: Programming Language :: Python :: 3
Classifier: License :: OSI Approved :: Apache Software License
Classifier: Development Status :: 2 - Pre-Alpha
Classifier: Operating System :: POSIX :: Linux
Classifier: Environment :: Console
Classifier: Topic :: Software Development :: Debuggers
Requires-Python: >=3.10
License-File: LICENSE.md
